dataanalyze/__init__.py
dataanalyze/analysis/__init__.py
dataanalyze/analysis/analysis_result.py
dataanalyze/analysis/analyze_core.py
dataanalyze/analysis/data_analyze.py
dataanalyze/analysis/system_log_analyze.py
dataanalyze/analysis/test_analyze.py
dataanalyze/datas/__init__.py
dataanalyze/datas/test_result_data.py
dataanalyze/rules/__init__.py
dataanalyze/rules/rule.py
dataanalyze/rules/rules.json
dataanalyze/rules/rules.py
dataanalyze/utils/__init__.py
dataanalyze/utils/read_file.py
data_analyze-1.4.1.dist-info/LICENSE
data_analyze-1.4.1.dist-info/METADATA
data_analyze-1.4.1.dist-info/WHEEL
data_analyze-1.4.1.dist-info/top_level.txt
data_analyze-1.4.1.dist-info/RECORD
