Metadata-Version: 2.1
Name: data-analyze
Version: 1.4.1
Summary: data-analyze
Home-page: https://markdown.felinae.net
Author: luchang
Author-email: chang.lu@rokid.com
License: UNKNOWN
Keywords: data analyze
Platform: UNKNOWN
Classifier: Programming Language :: Python
Classifier: Development Status :: 4 - Beta
Classifier: Operating System :: OS Independent
Classifier: License :: OSI Approved :: Apache Software License
Classifier: Framework :: Django
